msu_helpers/__init__.py
msu_helpers/database/__init__.py
msu_helpers/database/base.py
msu_helpers/database/db_constants.py
msu_helpers/database/extended.py
msu_helpers/database/managers.py
msu_helpers/database/models.py
msu_helpers/database/serializers.py
msu_helpers/http/__init__.py
msu_helpers/http/http_constants.py
msu_helpers/http/responses/__init__.py
msu_helpers/http/responses/common_response.py
msu_helpers-1.0.2.dist-info/METADATA
msu_helpers-1.0.2.dist-info/RECORD
msu_helpers-1.0.2.dist-info/WHEEL
msu_helpers-1.0.2.dist-info/top_level.txt
