Metadata-Version: 2.1
Name: msu-helpers
Version: 1.0.2
Summary: Package created for the university project to store common application logic in one place.I am pretty sure that you do not need it
Home-page: https://github.com/Ujinjinjin/msu_helpers
Author: ujinjinjin
Author-email: gallkam@outlook.com 
License: UNKNOWN
Keywords: pip,msu_sqluniversity
Platform: UNKNOWN
